abpower/__init__.py
abpower/cli/__init__.py
abpower/data/__init__.py
abpower/data/actual_forecast.py
abpower/data/base.py
abpower/data/current_supply_demand.py
abpower/data/daily_average_pool_price.py
abpower/data/ets.py
abpower/data/hourly_available_capability.py
abpower/data/peak_load_forecast.py
abpower/data/pool_price.py
abpower/data/supply_surplus.py
abpower/data/system_marginal_price.py
abpower/exceptions.py
abpower/parser/__init__.py
abpower/parser/actual_forecast.py
abpower/parser/base.py
abpower/parser/current_supply_demand.py
abpower/parser/daily_average_pool_price.py
abpower/parser/ets.py
abpower/parser/hourly_available_capability.py
abpower/parser/peak_load_forecast.py
abpower/parser/pool_price.py
abpower/parser/supply_surplus.py
abpower/parser/system_marginal_price.py
abpower/tests/__init__.py
abpower/tests/test_cli.py
abpower/tests/test_data.py
abpower/tests/test_parser.py
abpower-0.1.2.dist-info/LICENSE
abpower-0.1.2.dist-info/METADATA
abpower-0.1.2.dist-info/WHEEL
abpower-0.1.2.dist-info/entry_points.txt
abpower-0.1.2.dist-info/RECORD
