Metadata-Version: 2.1
Name: abpower
Version: 0.1.2
Summary: Python package for parsing publicly-available data from the AESO ETS
Author: Andy Smith
Author-email: andy@nsnw.ca
Requires-Python: >=3.12,<4.0
Classifier: Programming Language :: Python :: 3
Classifier: Programming Language :: Python :: 3.12
Requires-Dist: beautifulsoup4 (>=4.12.2,<5.0.0)
Requires-Dist: click (>=8.1.7,<9.0.0)
Requires-Dist: dateparser (>=1.2.0,<2.0.0)
Requires-Dist: pytz (>=2023.3.post1,<2024.0)
Requires-Dist: requests (>=2.31.0,<3.0.0)
Requires-Dist: rich (>=13.7.0,<14.0.0)
